[
  {
    "name": "Rade Serbedzija"
  },
  {
    "name": "Zoran Vanev"
  },
  {
    "name": "Zorica Brunclik"
  },
  {
    "name": "Ferid Avdić"
  },
  {
    "name": "Šaban Šaulić"
  },
  {
    "name": "Arsen Dedić"
  },
  {
    "name": "Bill Withers"
  },
  {
    "name": "Billy Joel"
  },
  {
    "name": "ZORICA KONDŽA & TEDI SPALATO"
  },
  {
    "name": "Bon Jovi"
  },
  {
    "name": "Brian Ferry"
  },
  {
    "name": "Bryan Ferry"
  },
  {
    "name": "Dobrovoljno Pevačko Drustvo"
  },
  {
    "name": "Dubioza Kolektiv"
  },
  {
    "name": "Džukele"
  },
  {
    "name": "Emir Hot"
  },
  {
    "name": "ET"
  },
  {
    "name": "Ðorde Balaševic"
  },
  {
    "name": "Nikola Cuturilo Bend"
  },
  {
    "name": "Džej Ramadanovski"
  },
  {
    "name": "Meho Puzić"
  },
  {
    "name": "Novica Negovanović"
  },
  {
    "name": "Predrag Živković Tozovac"
  },
  {
    "name": "BAKAPRASE"
  },
  {
    "name": "Balasevic I Jadranka Stojakovic"
  },
  {
    "name": "Bebi Dol"
  },
  {
    "name": "Beca Fantastik"
  },
  {
    "name": "Bisera Veletanlic"
  },
  {
    "name": "Boba Stefanović"
  },
  {
    "name": "Animals"
  },
  {
    "name": "Andonis Remos"
  },
  {
    "name": "Anastacia"
  },
  {
    "name": "Albino"
  },
  {
    "name": "Amadeus Band i Bora Corba"
  },
  {
    "name": "Allegro Band"
  },
  {
    "name": "Alen Ademovic cover (Buika)"
  },
  {
    "name": "Griva"
  },
  {
    "name": "Boris Novković & Tony Cetinski"
  },
  {
    "name": "Bora Spužić Kvaka"
  },
  {
    "name": "Dragica Radosavljević Cakana"
  },
  {
    "name": "Boris Rezak"
  },
  {
    "name": "Procol Harum"
  },
  {
    "name": "Al Dino"
  },
  {
    "name": "Pink Floyd"
  },
  {
    "name": "Bombaj Štampa"
  },
  {
    "name": "Buč Kesidi"
  },
  {
    "name": "Badrić Nina"
  },
  {
    "name": "Bane Opacic"
  },
  {
    "name": "Bilja Krstić i Bistrik"
  },
  {
    "name": "Damir Urban"
  },
  {
    "name": "Biljana Jeftić"
  },
  {
    "name": "Blizanci"
  },
  {
    "name": "Boban Zdravkovic"
  },
  {
    "name": "Bojan Bjelic feat Indy"
  },
  {
    "name": "Ibrica Jusić"
  },
  {
    "name": "Galija"
  },
  {
    "name": "Beti Đorđević"
  },
  {
    "name": "Bađi feat. Đani"
  },
  {
    "name": "Bojan Bajramovic"
  },
  {
    "name": "Bojan Petricevic"
  },
  {
    "name": "Bora Spužić Kvaka"
  },
  {
    "name": "Cure"
  },
  {
    "name": "Aazzrraa"
  },
  {
    "name": "Aca trendafilovic"
  },
  {
    "name": "Aleksandra Bursac i Vanja Lakatos"
  },
  {
    "name": "Aleksandra Cekić i Emir Đulović"
  },
  {
    "name": "Aretha Franklin"
  },
  {
    "name": "Ace Of Base"
  },
  {
    "name": "A.C.A.B"
  },
  {
    "name": "Boza Nikolic"
  },
  {
    "name": "Zvonko Demirović (Miljan.U)"
  },
  {
    "name": "Zvonko DemirovicDennis Alilovic"
  },
  {
    "name": "Aleksandra Kovač"
  },
  {
    "name": "Aleksandra Prijovic & Lexington band"
  },
  {
    "name": "Alen Islamović i Sanja Doležal"
  },
  {
    "name": "Arsen Dedic"
  },
  {
    "name": "100 Band"
  },
  {
    "name": "Aca Lukas (duet Ceca)"
  },
  {
    "name": "Aca Lukas i Danijela Vranić"
  },
  {
    "name": "Aca Lukas i Marija Serifovic"
  },
  {
    "name": "Acapulco Band"
  },
  {
    "name": "Adi Sose"
  },
  {
    "name": "Adnan I Tarik"
  },
  {
    "name": "Alegro bend"
  },
  {
    "name": "Cyndi Lauper"
  },
  {
    "name": "AmiG ×Young Pulk(Djans)"
  },
  {
    "name": "Armin Bijedić"
  },
  {
    "name": "Ana Bekuta"
  },
  {
    "name": "Amar Gile Jasarspahić"
  },
  {
    "name": "Angel Dimov"
  },
  {
    "name": "Ana Sofrenović"
  },
  {
    "name": "Andrijana Radonjic"
  },
  {
    "name": "Amela Zukovic"
  },
  {
    "name": "Amel i Kice"
  },
  {
    "name": "Amar Jasarspahic"
  },
  {
    "name": "Amar Gile"
  },
  {
    "name": "Amar Gile & Jelena Kostov"
  },
  {
    "name": "Zoran Kalezic"
  },
  {
    "name": "Branko Kockica"
  },
  {
    "name": "Colonia"
  },
  {
    "name": "Dado Topic"
  },
  {
    "name": "Darko Rundek"
  },
  {
    "name": "Dejan Cukić"
  },
  {
    "name": "Dino Merlin"
  },
  {
    "name": "Dino Merlin i Emina Jahovic"
  },
  {
    "name": "Divlje Jagode feat. Toni Jankovic"
  },
  {
    "name": "Eyesburn"
  },
  {
    "name": "Đorđe Balaševićv"
  },
  {
    "name": "Đorđe Bačašević"
  },
  {
    "name": "Cara Mimi i Zoran Šumadinac"
  },
  {
    "name": "Danka Stoiljkovic"
  },
  {
    "name": "Dusko Vulic Roca"
  },
  {
    "name": "Đokara i gnjurci"
  },
  {
    "name": "Cazim Colakovic"
  },
  {
    "name": "Dado Polumenta"
  },
  {
    "name": "Dara Bubamara"
  },
  {
    "name": "Darko Lazic"
  },
  {
    "name": "DeeDee Dinko (Acoustic)"
  },
  {
    "name": "Dejan Aličić"
  },
  {
    "name": "Dobrivoje Topalović"
  },
  {
    "name": "Dragan Gagi Jovanović"
  },
  {
    "name": "Dusan Svilar"
  },
  {
    "name": "Dušan Kostić"
  },
  {
    "name": "Dzenan Loncarevic"
  },
  {
    "name": "Emina feat. Milica Todorović"
  },
  {
    "name": "Emina Jahovic ft Sasa Kovacevic"
  },
  {
    "name": "Emina Jahović ft Milica Todorović"
  },
  {
    "name": "Emina Jahović ft. Zeljko Joksimovic"
  },
  {
    "name": "Esma Redžepova"
  },
  {
    "name": "Ferid Avdic"
  },
  {
    "name": "Chris Rea"
  },
  {
    "name": "Coldplay"
  },
  {
    "name": "David Bowie"
  },
  {
    "name": "Garavi sokak i Tamburasi"
  },
  {
    "name": "Garavi Sokak uzivo"
  },
  {
    "name": "Goran Karan, Severina, Guliano"
  },
  {
    "name": "Fikret Dudevic Pike"
  },
  {
    "name": "Halid Beslic ft Legende"
  },
  {
    "name": "Don Mclean"
  },
  {
    "name": "ED SHEERAN"
  },
  {
    "name": "Eric Clapton"
  },
  {
    "name": "Europe"
  },
  {
    "name": "Film"
  },
  {
    "name": "Frajle"
  },
  {
    "name": "Gibonni"
  },
  {
    "name": "Goca Trzan"
  },
  {
    "name": "Goca Trzan Zlatko Vujic"
  },
  {
    "name": "Hladno Pivo"
  },
  {
    "name": "Hurricane"
  },
  {
    "name": "In Vivo"
  },
  {
    "name": "Ivan Bosiljčić"
  },
  {
    "name": "Ivana Jordan"
  },
  {
    "name": "Goran Bregovic"
  },
  {
    "name": "Gordana Stojicevic Goca"
  },
  {
    "name": "Halid Beslic (M)"
  },
  {
    "name": "Hamo i Soso"
  },
  {
    "name": "Hanka Paldum"
  },
  {
    "name": "Hasan Dudic (M)"
  },
  {
    "name": "Indira Radic Feat Pedja Medenica"
  },
  {
    "name": "Krunislav Kico Slabinac"
  },
  {
    "name": "Hasan Dudic"
  },
  {
    "name": "Indira Radic"
  },
  {
    "name": "Indira Radić & Alen Islamović"
  },
  {
    "name": "Indita Radić"
  },
  {
    "name": "Foo Fighters"
  },
  {
    "name": "Foreigner"
  },
  {
    "name": "Gary Moore"
  },
  {
    "name": "Goo Goo Dolls"
  },
  {
    "name": "Green Day"
  },
  {
    "name": "Iggy Pop"
  },
  {
    "name": "Jadranka Stojakovic"
  },
  {
    "name": "Jelena Rozga"
  },
  {
    "name": "Jelena Tomasevic"
  },
  {
    "name": "Karolina Gočeva"
  },
  {
    "name": "Kemal Monteno i Dusan Svilar"
  },
  {
    "name": "Kiki Lesandric i Piloti"
  },
  {
    "name": "Knez"
  },
  {
    "name": "Kolja i Smak Bijelog Dugmeta"
  },
  {
    "name": "Krunoslav Kićo Slabinac"
  },
  {
    "name": "Jelena Karleuša"
  },
  {
    "name": "Klapa Kumpanji"
  },
  {
    "name": "Klapa Rišpet i Jelena Rozga"
  },
  {
    "name": "John Legend"
  },
  {
    "name": "Journey"
  },
  {
    "name": "Laufer"
  },
  {
    "name": "Leontina"
  },
  {
    "name": "Magazin"
  },
  {
    "name": "Magnifico feat. Nikola Pejaković"
  },
  {
    "name": "Maja Odjaklievska"
  },
  {
    "name": "Marko Louis"
  },
  {
    "name": "MC Stojan & Hurricane"
  },
  {
    "name": "MC Stojan"
  },
  {
    "name": "Miki Jevremović"
  },
  {
    "name": "Mišo Kovač"
  },
  {
    "name": "Mladen Vojičić Tifa i grupa TOP"
  },
  {
    "name": "Legende i Zeljko Samardzic"
  },
  {
    "name": "Ljubiša Stojanović Luis"
  },
  {
    "name": "Ljubo Keselj"
  },
  {
    "name": "Milance Radosaljevic"
  },
  {
    "name": "Milivoj Lemi Mrdaković"
  },
  {
    "name": "Levko Timoщuk (Levko Tymoščuk)"
  },
  {
    "name": "Nesko Kejdz"
  },
  {
    "name": "Marija Šerifović"
  },
  {
    "name": "Marinko Madžgalj"
  },
  {
    "name": "Marinko Rokvic"
  },
  {
    "name": "Marko Rokvić"
  },
  {
    "name": "Meho Puzić"
  },
  {
    "name": "Milan Stankovic"
  },
  {
    "name": "Milica"
  },
  {
    "name": "Miroslav Ilić"
  },
  {
    "name": "Miroslav Škoro"
  },
  {
    "name": "Mirza Selimović"
  },
  {
    "name": "Muharem Serbezovski"
  },
  {
    "name": "Los Lobos"
  },
  {
    "name": "Lost Frequencies"
  },
  {
    "name": "Metallica"
  },
  {
    "name": "Moloko"
  },
  {
    "name": "Natasa Bekvalac ft. Coby"
  },
  {
    "name": "Neno Belan"
  },
  {
    "name": "No smoking orcestra"
  },
  {
    "name": "Nedzad Esadovic"
  },
  {
    "name": "Pedja Medanica"
  },
  {
    "name": "Nikola Pejaković"
  },
  {
    "name": "Ogi"
  },
  {
    "name": "Oliver Dragojevic"
  },
  {
    "name": "Oliver Mandic feat Ceca"
  },
  {
    "name": "Oružjem Protiv Otmičara"
  },
  {
    "name": "Parni Valjak"
  },
  {
    "name": "Petar Grašo"
  },
  {
    "name": "Psihomodo Pop"
  },
  {
    "name": "Nada Topcagic"
  },
  {
    "name": "Neda Ukraden"
  },
  {
    "name": "Nedjeljko Bilkić"
  },
  {
    "name": "Nedžad Salković"
  },
  {
    "name": "Nikola Rokvić"
  },
  {
    "name": "Nino"
  },
  {
    "name": "Ok Band"
  },
  {
    "name": "Perper"
  },
  {
    "name": "Predrag Živković Tozovac"
  },
  {
    "name": "Nahko Bear"
  },
  {
    "name": "Neil Young"
  },
  {
    "name": "Razni Izvodjaci"
  },
  {
    "name": "Regina"
  },
  {
    "name": "Riva"
  },
  {
    "name": "Ruž"
  },
  {
    "name": "Patrizzio Buanne"
  },
  {
    "name": "S.A.R.S"
  },
  {
    "name": "Senidah"
  },
  {
    "name": "Sergej Cetkovic"
  },
  {
    "name": "Smak"
  },
  {
    "name": "Rodja Raicevic"
  },
  {
    "name": "S.A.R.S. & Veseli drugari"
  },
  {
    "name": "sjecas li se doly bell"
  },
  {
    "name": "Rade Kosmajac & Djani"
  },
  {
    "name": "Savo Radosinovic"
  },
  {
    "name": "Oasis"
  },
  {
    "name": "R.E.M"
  },
  {
    "name": "Srebrna Krila"
  },
  {
    "name": "Suncokret"
  },
  {
    "name": "Zeljko Vasic"
  },
  {
    "name": "Štublić Jura"
  },
  {
    "name": "Rade Jorović"
  },
  {
    "name": "Radisa Urosevic"
  },
  {
    "name": "Rok ko fol"
  },
  {
    "name": "Sasa Matic & Aleksandra Prijovic"
  },
  {
    "name": "Sasa Matic ft. JK"
  },
  {
    "name": "Sloba Bajić i Dejan Petrović Big Band"
  },
  {
    "name": "Stania Stošić"
  },
  {
    "name": "Serif Konjevic"
  },
  {
    "name": "Sevdalinke (M)"
  },
  {
    "name": "Sladja Alegro"
  },
  {
    "name": "Slobodan Djurkovic"
  },
  {
    "name": "Snezana Babic Sneki"
  },
  {
    "name": "Snezana Djurisic"
  },
  {
    "name": "Starogradska"
  },
  {
    "name": "Starogradski Biseri"
  },
  {
    "name": "Stoja"
  },
  {
    "name": "Šaban Šaulić (M)"
  },
  {
    "name": "Šeki Turković"
  },
  {
    "name": "Rufus Wainwright"
  },
  {
    "name": "Ruska Pesma"
  },
  {
    "name": "Ruske narodne pesme"
  },
  {
    "name": "Simply Red"
  },
  {
    "name": "Styx"
  },
  {
    "name": "Teska Industrija"
  },
  {
    "name": "Tifa"
  },
  {
    "name": "Tropico Band ft. Aco Pejovic"
  },
  {
    "name": "Tropico Band ft. Ministarke"
  },
  {
    "name": "The Remembrants"
  },
  {
    "name": "Vojvodjanski Blues Band"
  },
  {
    "name": "Tijana Dapčević(Sakis Rouvas)"
  },
  {
    "name": "Time"
  },
  {
    "name": "Tony Cetinski"
  },
  {
    "name": "Tropico Band feat. Dzenan Loncarevic"
  },
  {
    "name": "Tunel"
  },
  {
    "name": "TAMBURASI ZA DUSU"
  },
  {
    "name": "Tamburaši"
  },
  {
    "name": "Tanja Savić x Rimski"
  },
  {
    "name": "Tomislav Čolović"
  },
  {
    "name": "Tenacious D"
  },
  {
    "name": "Tina Turner"
  },
  {
    "name": "Toygar Işıklı"
  },
  {
    "name": "Van Gogh"
  },
  {
    "name": "Vesna Pisarović"
  },
  {
    "name": "Vlada Divljan i Srdjan Gile Gojkovic"
  },
  {
    "name": "Vlado Georgijev"
  },
  {
    "name": "Vlado Kalember"
  },
  {
    "name": "Vuk Mob"
  },
  {
    "name": "Yu Grupa"
  },
  {
    "name": "Željko Samrardžić"
  },
  {
    "name": "Verica Serifovic acordi"
  },
  {
    "name": "Zika Marinkovic Sumac"
  },
  {
    "name": "Hačim Kučuk Hoki"
  },
  {
    "name": "Haris Džinović "
  },
  {
    "name": "Zoran Kulina"
  },
  {
    "name": "Zoran Misic"
  },
  {
    "name": "Zeljko Samardzic"
  },
  {
    "name": "Zeljko Vasic i Nina Badric"
  },
  {
    "name": "Uroš Živković"
  },
  {
    "name": "Vesna Zmijanac i Slavko Banjac"
  },
  {
    "name": "Zlatan Fazlić Fazla"
  },
  {
    "name": "U 2"
  },
  {
    "name": "U2"
  },
  {
    "name": "Van Halen"
  },
  {
    "name": "Wiz Khalifia"
  },
  {
    "name": "Yazoo"
  },
  {
    "name": "Zoran Predin"
  },
  {
    "name": "Toma Zdravković"
  },
  {
    "name": "Zorana & Mateja Kežman"
  },
  {
    "name": "Zorana Pavić i Đorđe Pantić"
  },
  {
    "name": "Dobrivoje Topalović"
  },
  {
    "name": "Beatles"
  },
  {
    "name": "Bajaga i Miloš Biković"
  },
  {
    "name": "Halid Muslimović"
  },
  {
    "name": "Jahija Gračanlić"
  },
  {
    "name": "Lexington"
  },
  {
    "name": "Zorica Marković"
  },
  {
    "name": "B. J. Thomas"
  },
  {
    "name": "Beatles (The)"
  },
  {
    "name": "Bajaga, Point blank, Dragi Jelic"
  },
  {
    "name": "Bee Gees"
  },
  {
    "name": "Ben E. King"
  },
  {
    "name": "Bajaga"
  },
  {
    "name": "Billy Idol"
  },
  {
    "name": "Black"
  },
  {
    "name": "Blind Guardian"
  },
  {
    "name": "Blondie"
  },
  {
    "name": "Baka Prase"
  },
  {
    "name": "123"
  },
  {
    "name": "Bob Dylan"
  },
  {
    "name": "Bob Marley"
  },
  {
    "name": "Bobby Blue Bland"
  },
  {
    "name": "Brucia la terra"
  },
  {
    "name": "Bruno Mars"
  },
  {
    "name": "Bryan Adams"
  },
  {
    "name": "Brzi"
  },
  {
    "name": "Buddy Holly"
  },
  {
    "name": "Doris Dragovic"
  },
  {
    "name": "Dr iggy"
  },
  {
    "name": "Dragan Toković"
  },
  {
    "name": "Drugi Način"
  },
  {
    "name": "Dubrovački Trubaduri"
  },
  {
    "name": "Silvana Armenulić"
  },
  {
    "name": "BENI NON STOP"
  },
  {
    "name": "Dusko Lokin"
  },
  {
    "name": "Dušan Prelević Prele"
  },
  {
    "name": "Dža Ili Bu"
  },
  {
    "name": "Džentlmeni"
  },
  {
    "name": "E.T"
  },
  {
    "name": "Ekatarina Velika"
  },
  {
    "name": "Čutura"
  },
  {
    "name": "Elektricni orgazam"
  },
  {
    "name": "Elvis J. Kurtović"
  },
  {
    "name": "Eva Braun"
  },
  {
    "name": "Čovek Bez Sluha"
  },
  {
    "name": "Bajaga i Bebi Dol"
  },
  {
    "name": "Louis"
  },
  {
    "name": "Olivera Katarina"
  },
  {
    "name": "Predrag Cune Gojković"
  },
  {
    "name": "Pedja Medenica"
  },
  {
    "name": "Rade Jorović"
  },
  {
    "name": "Šako Polumenta"
  },
  {
    "name": "Beat Street"
  },
  {
    "name": "Zoran Gajić"
  },
  {
    "name": "Baki B3"
  },
  {
    "name": "Balkan"
  },
  {
    "name": "Bane Lalić & MVP"
  },
  {
    "name": "Bek-Sten"
  },
  {
    "name": "Beogradski Sindikat"
  },
  {
    "name": "Beti Đorđević"
  },
  {
    "name": "Big Blue"
  },
  {
    "name": "BIS BES"
  },
  {
    "name": "Bisera Valentić"
  },
  {
    "name": "Bjesovi"
  },
  {
    "name": "Alen Muković"
  },
  {
    "name": "Divlje Jagode"
  },
  {
    "name": "Block out"
  },
  {
    "name": "Bojan Marovic"
  },
  {
    "name": "Bolji život"
  },
  {
    "name": "Annie and Hayden"
  },
  {
    "name": "Amy Winehouse"
  },
  {
    "name": "ana"
  },
  {
    "name": "Alphaville"
  },
  {
    "name": "Alice Cooper"
  },
  {
    "name": "Alan Walker"
  },
  {
    "name": "Amadeus Bend"
  },
  {
    "name": "Amadeus Band"
  },
  {
    "name": "Amadeus"
  },
  {
    "name": "Alen Slavica"
  },
  {
    "name": "Black Panters"
  },
  {
    "name": "alen ademovic"
  },
  {
    "name": "Aleksandra Mladenovic"
  },
  {
    "name": "Aco Pejović"
  },
  {
    "name": "Ajnur Serbezovski"
  },
  {
    "name": "Radiša Marković"
  },
  {
    "name": "Boris Novković"
  },
  {
    "name": "Breskvica"
  },
  {
    "name": "Brkovi"
  },
  {
    "name": "Buba Corelli"
  },
  {
    "name": "Toni Cetinski"
  },
  {
    "name": "Zoster"
  },
  {
    "name": "Zvezdine pesme"
  },
  {
    "name": "Đorđe Balašević"
  },
  {
    "name": "Badji"
  },
  {
    "name": "Bagra ft. Incident"
  },
  {
    "name": "Baja Mali Knindža"
  },
  {
    "name": "Indexi"
  },
  {
    "name": "Babe"
  },
  {
    "name": "Bajko"
  },
  {
    "name": "Baklava"
  },
  {
    "name": "Bane Bojanić"
  },
  {
    "name": "Bijelo Dugme"
  },
  {
    "name": "Bogdan Grujić"
  },
  {
    "name": "Bane Mojicevic"
  },
  {
    "name": "Baruni"
  },
  {
    "name": "Bolero"
  },
  {
    "name": "Bombaj Štampa"
  },
  {
    "name": "Beki Bekic"
  },
  {
    "name": "Crvena Jabuka"
  },
  {
    "name": "Dado Topić"
  },
  {
    "name": "Drugi Način"
  },
  {
    "name": "Ekatarina velika"
  },
  {
    "name": "Miladin Šobic"
  },
  {
    "name": "Biljana Jevtic"
  },
  {
    "name": "Black Panthers"
  },
  {
    "name": "Boban Rajovic i Dragana Mirkovic"
  },
  {
    "name": "Boban Rajović"
  },
  {
    "name": "Bojan Jambrošić"
  },
  {
    "name": "Bojan Tomović"
  },
  {
    "name": "Boje Noci"
  },
  {
    "name": "Boki Tatko"
  },
  {
    "name": "Bon Ami"
  },
  {
    "name": "Bora Drljaca"
  },
  {
    "name": "Aco Regina"
  },
  {
    "name": "acoustic"
  },
  {
    "name": "Aleksa Jelić"
  },
  {
    "name": "Aleksandar Radović"
  },
  {
    "name": "Aleksandra Prijovic"
  },
  {
    "name": "Aleksandra Radovic"
  },
  {
    "name": "Alen Islamović"
  },
  {
    "name": "Aleksandar Aca Ilić"
  },
  {
    "name": "Alen Islamović i Indira"
  },
  {
    "name": "Alisa"
  },
  {
    "name": "Alogia"
  },
  {
    "name": "Ambasadori"
  },
  {
    "name": "Ana Stanić"
  },
  {
    "name": "Andjelka Govedarović"
  },
  {
    "name": "Ana Stanić ft Wikluh Sky"
  },
  {
    "name": "Anastasija"
  },
  {
    "name": "Animatori"
  },
  {
    "name": "Area"
  },
  {
    "name": "Arhangel"
  },
  {
    "name": "Atheist Rap"
  },
  {
    "name": "Atomsko Sklonište"
  },
  {
    "name": "A.M."
  },
  {
    "name": "Aca Ilić"
  },
  {
    "name": "Aca Lukas"
  },
  {
    "name": "Aca Lukas i Ivana Selakov"
  },
  {
    "name": "Aca Mika Alas"
  },
  {
    "name": "Aca Zivanovic & Gabrijela Pejčev"
  },
  {
    "name": "Aca Zivanovic"
  },
  {
    "name": "Aco Pejovic"
  },
  {
    "name": "Aco Pejović i Aleksandra Prijovic"
  },
  {
    "name": "Adil"
  },
  {
    "name": "adil i alegro bend"
  },
  {
    "name": "Adil i Marija Serifovic"
  },
  {
    "name": "Adnan Jakupović"
  },
  {
    "name": "Ado Gegaj"
  },
  {
    "name": "Ahmet Rasimov"
  },
  {
    "name": "Aleksandar Mezek"
  },
  {
    "name": "Aleksandra Cekic"
  },
  {
    "name": "Avicii"
  },
  {
    "name": "Astor Piazzola"
  },
  {
    "name": "Arctic Monkeys"
  },
  {
    "name": "Aerosmith"
  },
  {
    "name": "Adele"
  },
  {
    "name": "Adela Secic"
  },
  {
    "name": "Adam Lambert"
  },
  {
    "name": "AC-DC"
  },
  {
    "name": "Abba"
  },
  {
    "name": "4 Non Blondes"
  },
  {
    "name": "3 Doors Down"
  },
  {
    "name": "Ѓorѓi Krstevski"
  },
  {
    "name": "Zvonko Milenković"
  },
  {
    "name": "Trip At 7"
  },
  {
    "name": "Božo Vorotović"
  },
  {
    "name": "Božo Vrećo"
  },
  {
    "name": "Branka Sovrlić"
  },
  {
    "name": "Zvonko Demirovic"
  },
  {
    "name": "Zvonko Bogdan"
  },
  {
    "name": "Zvijezda tjera mjeseca"
  },
  {
    "name": "Asim Brkan"
  },
  {
    "name": "Asim Brkan (M)"
  },
  {
    "name": "Asim Bajrić"
  },
  {
    "name": "Armin Sakovic"
  },
  {
    "name": "Andreana Čekić & Emir Đulović"
  },
  {
    "name": "Eagles"
  },
  {
    "name": "Armin Muzaferija"
  },
  {
    "name": "Armin Malikić"
  },
  {
    "name": "Armin Dedic"
  },
  {
    "name": "Arabeske i Zabranjeno pušenje"
  },
  {
    "name": "Apsolutno Romantično"
  },
  {
    "name": "Amira Medunjanin"
  },
  {
    "name": "Antonija sola"
  },
  {
    "name": "Anid Cusic"
  },
  {
    "name": "Angellina"
  },
  {
    "name": "Aneta Micevska"
  },
  {
    "name": "Andreana Cekic"
  },
  {
    "name": "Ana Nikolic"
  },
  {
    "name": "Anastasija Ražnatović"
  },
  {
    "name": "Andrej Dorić"
  },
  {
    "name": "Amir Nino Rešić"
  },
  {
    "name": "Amir Kazić Leo"
  },
  {
    "name": "AmiG"
  },
  {
    "name": "Amel Ćurić"
  },
  {
    "name": "Hadži Prodane DuŠe"
  },
  {
    "name": "Amel Curic feat Emina Jahovic"
  },
  {
    "name": "Amadeus Bend i Bora Čorba"
  },
  {
    "name": "Aziz Alili"
  },
  {
    "name": "Zoka Bosanac"
  },
  {
    "name": "Zona Zamfirova"
  },
  {
    "name": "Zona Zamfirova 2 (Milan Vasić)"
  },
  {
    "name": "Zoran Gajić"
  },
  {
    "name": "Zoran Janković"
  },
  {
    "name": "Zoran Jovanović"
  },
  {
    "name": "Corona x Rimski"
  },
  {
    "name": "Dalmatino"
  },
  {
    "name": "Crvena Jabuka i Kemal Monteno"
  },
  {
    "name": "Crvena zvezda"
  },
  {
    "name": "Crveni koralji"
  },
  {
    "name": "Daleka Obala"
  },
  {
    "name": "Dalmatio"
  },
  {
    "name": "Darko Domijan"
  },
  {
    "name": "Davorin Popović"
  },
  {
    "name": "Debeli Precjednik"
  },
  {
    "name": "Decije"
  },
  {
    "name": "Dee Monk"
  },
  {
    "name": "Dejan Petković"
  },
  {
    "name": "Del Arno Band"
  },
  {
    "name": "Denis & Denis"
  },
  {
    "name": "Dino Dvornik"
  },
  {
    "name": "Divanhana"
  },
  {
    "name": "Divlji Anđeli"
  },
  {
    "name": "Divlji Kesten"
  },
  {
    "name": "Đavoli"
  },
  {
    "name": "Đogani"
  },
  {
    "name": "Đorđe Marijanović"
  },
  {
    "name": "Đorđe Miljenović (Wikluh Sky)"
  },
  {
    "name": "In Vivo & Leon feat. DJ TAZZ"
  },
  {
    "name": "Đorđe Miljenović"
  },
  {
    "name": "Cakana"
  },
  {
    "name": "Ceca"
  },
  {
    "name": "Cetnicka"
  },
  {
    "name": "Cetnicke"
  },
  {
    "name": "Ciganske"
  },
  {
    "name": "Crkveni hor"
  },
  {
    "name": "Dona Ares"
  },
  {
    "name": "Crni"
  },
  {
    "name": "Dado Glišić"
  },
  {
    "name": "Dado Polumenta i Aleksandar Domić"
  },
  {
    "name": "Darko Lazić i Anid Ćušić"
  },
  {
    "name": "Darko Lazić i Rada Manojlović"
  },
  {
    "name": "Dejan Matic"
  },
  {
    "name": "Dejan Matić & Romana"
  },
  {
    "name": "Dejan Matić i Goran Trivić"
  },
  {
    "name": "Dejan Petrović Big Band"
  },
  {
    "name": "DJ Krmak"
  },
  {
    "name": "Djani"
  },
  {
    "name": "Donna Ares"
  },
  {
    "name": "Dragan Jovanović"
  },
  {
    "name": "Dragan Kojić Keba & Ceca"
  },
  {
    "name": "Dragan Kojić Keba"
  },
  {
    "name": "Dragana Mirkovic"
  },
  {
    "name": "Duško Kostić"
  },
  {
    "name": "Duško Kuliš"
  },
  {
    "name": "Dzej"
  },
  {
    "name": "Dzejla Ramovic"
  },
  {
    "name": "Dženan Lončarević i Tropico"
  },
  {
    "name": "Edo"
  },
  {
    "name": "Elma Sinanovic"
  },
  {
    "name": "Emina Jahović"
  },
  {
    "name": "Enes Begović"
  },
  {
    "name": "Era Ojdanic"
  },
  {
    "name": "Esad Plavi"
  },
  {
    "name": "Etno grupa Trag"
  },
  {
    "name": "In Vivo & Leon Ft. DJ Tazz"
  },
  {
    "name": "Etno Pesme"
  },
  {
    "name": "Fadil Toskic"
  },
  {
    "name": "Čeda Marković"
  },
  {
    "name": "Cake"
  },
  {
    "name": "Carlos Santana"
  },
  {
    "name": "Celine Dion"
  },
  {
    "name": "Chris Cornell"
  },
  {
    "name": "D.H.T."
  },
  {
    "name": "Chris Isaak"
  },
  {
    "name": "Christina Perri"
  },
  {
    "name": "christina perry"
  },
  {
    "name": "Cranberries"
  },
  {
    "name": "Cream"
  },
  {
    "name": "Creedence Clearwater Revival"
  },
  {
    "name": "Daft Punk"
  },
  {
    "name": "David Bisbal"
  },
  {
    "name": "Deep Purple"
  },
  {
    "name": "Depeche Mode"
  },
  {
    "name": "Derek And The Dominos"
  },
  {
    "name": "Disturbed"
  },
  {
    "name": "Dwayne Johnson (The Rock)"
  },
  {
    "name": "Eddie Vedder"
  },
  {
    "name": "Elvis Presley"
  },
  {
    "name": "Emeli Sandé"
  },
  {
    "name": "Emerson Lake & Palmer"
  },
  {
    "name": "En Vogue"
  },
  {
    "name": "In Vivo ft. Generacija 5"
  },
  {
    "name": "Eros Ramazzotti"
  },
  {
    "name": "Eurythmics"
  },
  {
    "name": "Evanescence"
  },
  {
    "name": "Faith No More"
  },
  {
    "name": "Familija"
  },
  {
    "name": "Fit"
  },
  {
    "name": "Flamingosi"
  },
  {
    "name": "Funky G"
  },
  {
    "name": "Gabi Novak"
  },
  {
    "name": "Garavi Sokak"
  },
  {
    "name": "Generacija 5"
  },
  {
    "name": "Generacija bez kompasa"
  },
  {
    "name": "Goblini"
  },
  {
    "name": "Goran Karan"
  },
  {
    "name": "Ritam Nereda"
  },
  {
    "name": "Hari Mata Hari"
  },
  {
    "name": "Hari Mata Hari i Nina"
  },
  {
    "name": "Haustor"
  },
  {
    "name": "Henda"
  },
  {
    "name": "Ibrica Jusic"
  },
  {
    "name": "Idoli"
  },
  {
    "name": "ITD Band"
  },
  {
    "name": "Ivan Gavrilović"
  },
  {
    "name": "Ferid Avdić (M)"
  },
  {
    "name": "Gagi bend"
  },
  {
    "name": "Goca Bozinovska"
  },
  {
    "name": "Goca Lazarević"
  },
  {
    "name": "Kaliopi"
  },
  {
    "name": "Goran Dima"
  },
  {
    "name": "Gordana Lazarević"
  },
  {
    "name": "Gordana Stojicevic"
  },
  {
    "name": "Gradske Cure"
  },
  {
    "name": "Halid Beslic"
  },
  {
    "name": "Halid Muslimović"
  },
  {
    "name": "Klapa Rispet"
  },
  {
    "name": "Suncokreti"
  },
  {
    "name": "Hamza Skrijelj"
  },
  {
    "name": "Još ovu noć"
  },
  {
    "name": "Haris Berkovic i Rada Manojlovic"
  },
  {
    "name": "Haris Dzinovic"
  },
  {
    "name": "Hašim Kučuk Hoki"
  },
  {
    "name": "Himna"
  },
  {
    "name": "Himne"
  },
  {
    "name": "Himzo Polovina"
  },
  {
    "name": "Ilda Šaulić"
  },
  {
    "name": "Ipče Ahmedovski"
  },
  {
    "name": "Izvorna muzika"
  },
  {
    "name": "Izvorna pesma"
  },
  {
    "name": "Fleetwood Mac"
  },
  {
    "name": "Justin Bieber"
  },
  {
    "name": "Fool's Garden"
  },
  {
    "name": "Frank Sinatra"
  },
  {
    "name": "Gabriella Cilmi"
  },
  {
    "name": "Game of Thrones"
  },
  {
    "name": "George Michael"
  },
  {
    "name": "Gilbert Bécaud"
  },
  {
    "name": "Gipsy Kings"
  },
  {
    "name": "Gotye"
  },
  {
    "name": "Grčka narodna pesma"
  },
  {
    "name": "Grčke Pesme"
  },
  {
    "name": "Guns N' Roses"
  },
  {
    "name": "Halestorm"
  },
  {
    "name": "Haymaker"
  },
  {
    "name": "Heidi (Jetlag Production)"
  },
  {
    "name": "HIM"
  },
  {
    "name": "Milica Pavlović"
  },
  {
    "name": "Imagination"
  },
  {
    "name": "Indila"
  },
  {
    "name": "Inner Circle"
  },
  {
    "name": "Irish Stew Of Sindidun"
  },
  {
    "name": "Jala Brat & Buba Corelli"
  },
  {
    "name": "Jala Brat"
  },
  {
    "name": "Jala Brat x Buba Corelli"
  },
  {
    "name": "Jala Brat x Buba Corelli x Senidah"
  },
  {
    "name": "Josipa Lisac"
  },
  {
    "name": "Jura Stublic & Film"
  },
  {
    "name": "Karolina i Vlatko Stefanovski"
  },
  {
    "name": "Kemal Monteno"
  },
  {
    "name": "Kerber"
  },
  {
    "name": "Kiki Lesendrić"
  },
  {
    "name": "Kolja i grobovlasnici"
  },
  {
    "name": "Košava"
  },
  {
    "name": "Kansas"
  },
  {
    "name": "Kraljevski Apartman"
  },
  {
    "name": "Ksenija Mijatovic"
  },
  {
    "name": "Kud Idijoti"
  },
  {
    "name": "Kuguars"
  },
  {
    "name": "Laboratorija Zvuka"
  },
  {
    "name": "Lacni Franz"
  },
  {
    "name": "Kelly Family"
  },
  {
    "name": "Jahija Gračanlić"
  },
  {
    "name": "Jami"
  },
  {
    "name": "Jasar Ahmedovski"
  },
  {
    "name": "Jovica Simic"
  },
  {
    "name": "Kiki Lesendrić"
  },
  {
    "name": "Metak"
  },
  {
    "name": "Juzni Vetar"
  },
  {
    "name": "Kaya"
  },
  {
    "name": "Keba"
  },
  {
    "name": "Kemal Malovcic"
  },
  {
    "name": "klapa"
  },
  {
    "name": "Klapa Bili Čiku"
  },
  {
    "name": "KLAPA KAMPANEL"
  },
  {
    "name": "Klapa Šufit"
  },
  {
    "name": "Ko to tamo peva"
  },
  {
    "name": "James Arthur"
  },
  {
    "name": "Jimi Hendrix"
  },
  {
    "name": "Joan Osborne"
  },
  {
    "name": "Milica Todorović"
  },
  {
    "name": "Joe Dassin"
  },
  {
    "name": "John Denver"
  },
  {
    "name": "John Lennon"
  },
  {
    "name": "Johnny Nash"
  },
  {
    "name": "Jorgos Dalaras"
  },
  {
    "name": "Kenny Rodgers"
  },
  {
    "name": "Killing Me Softly"
  },
  {
    "name": "Kings of Leon"
  },
  {
    "name": "Kinks"
  },
  {
    "name": "Kiss From A Rose"
  },
  {
    "name": "Kygo"
  },
  {
    "name": "Laki Pingvini"
  },
  {
    "name": "Leb i Sol"
  },
  {
    "name": "Lena Kovačević"
  },
  {
    "name": "Leo Martin"
  },
  {
    "name": "Neverne Bebe"
  },
  {
    "name": "Letu Štuke"
  },
  {
    "name": "Love Hunters"
  },
  {
    "name": "Madam Piano & Orthodox Celts"
  },
  {
    "name": "Madam Piano"
  },
  {
    "name": "magazin i tifa"
  },
  {
    "name": "Lady Gaga and Bradley Cooper"
  },
  {
    "name": "Magnifico"
  },
  {
    "name": "Maja Odzaklijevska"
  },
  {
    "name": "Majke"
  },
  {
    "name": "Marina Perazic"
  },
  {
    "name": "Massimo Savic"
  },
  {
    "name": "Max i Rade Šerbedžija"
  },
  {
    "name": "Maya Berović"
  },
  {
    "name": "Maya Berović feat. Buba Corelli"
  },
  {
    "name": "Meri Cetinic"
  },
  {
    "name": "Merlin"
  },
  {
    "name": "merlin i vesna"
  },
  {
    "name": "Mikula"
  },
  {
    "name": "Miladin Sobic"
  },
  {
    "name": "Milić Vukašinović"
  },
  {
    "name": "Minja Subota"
  },
  {
    "name": "Mladen Vojičić Tifa"
  },
  {
    "name": "Lexington Band"
  },
  {
    "name": "Moby Dick"
  },
  {
    "name": "MVP"
  },
  {
    "name": "Legende"
  },
  {
    "name": "Lepa Brena"
  },
  {
    "name": "Lepa Lukić"
  },
  {
    "name": "Lepi Mica"
  },
  {
    "name": "Mile Kitic"
  },
  {
    "name": "Ljuba Alicic"
  },
  {
    "name": "Ljuba Aličić (M)"
  },
  {
    "name": "Ljuba Lukić"
  },
  {
    "name": "Luis"
  },
  {
    "name": "Magla band"
  },
  {
    "name": "Magla Bend & Natasa Bekvalac"
  },
  {
    "name": "Magla Bend"
  },
  {
    "name": "Maja Marijana"
  },
  {
    "name": "Makedonske Pesme"
  },
  {
    "name": "Marija Šerifović i Adil"
  },
  {
    "name": "Marko Bulat"
  },
  {
    "name": "Marko Perkovic Thompson"
  },
  {
    "name": "Marko Tomasovic"
  },
  {
    "name": "Medeni Mesec"
  },
  {
    "name": "Merima Njegomir"
  },
  {
    "name": "Miki Mecava"
  },
  {
    "name": "Milan Babić"
  },
  {
    "name": "Milan Dinčić Dinča"
  },
  {
    "name": "Milan Topalović Topalko"
  },
  {
    "name": "Milance Radosavljevic"
  },
  {
    "name": "Miligram"
  },
  {
    "name": "Miligram feat. Ivana"
  },
  {
    "name": "Milos Bikovic"
  },
  {
    "name": "Miloš Bojanić"
  },
  {
    "name": "Mira Skoric"
  },
  {
    "name": "Muzika iz filma Zona Zamfirova 2"
  },
  {
    "name": "Mirko Rondovic"
  },
  {
    "name": "Miroljub Brzaković Brzi"
  },
  {
    "name": "Miroslav Ilić  (M)"
  },
  {
    "name": "Mirza Selimović & Ivana Selakov"
  },
  {
    "name": "Mitar Mirić"
  },
  {
    "name": "Mostar sevdah reunion"
  },
  {
    "name": "Lady Gaga & Bradley Cooper"
  },
  {
    "name": "Led Zeppelin"
  },
  {
    "name": "Lenny Kravitz"
  },
  {
    "name": "Leonard Cohen"
  },
  {
    "name": "LP"
  },
  {
    "name": "Lucio Dalla"
  },
  {
    "name": "Luis Fonsi ft. Daddy Yankee"
  },
  {
    "name": "LYNYRD SKYNYRD"
  },
  {
    "name": "Nervozni Poštar"
  },
  {
    "name": "Mando Diao"
  },
  {
    "name": "Maneskin"
  },
  {
    "name": "Maroon 5"
  },
  {
    "name": "Metalica"
  },
  {
    "name": "Michel Teló"
  },
  {
    "name": "Mike Oldfield"
  },
  {
    "name": "Milow"
  },
  {
    "name": "Moody Blues"
  },
  {
    "name": "Morcheeba"
  },
  {
    "name": "Motorhead"
  },
  {
    "name": "Natasa Bekvalac"
  },
  {
    "name": "Neki To Vole Vruće"
  },
  {
    "name": "Nenad Knezević Knez"
  },
  {
    "name": "Nikola Cuturilo Cutura"
  },
  {
    "name": "Nikola Kojo"
  },
  {
    "name": "Nikola Pejakovic Kolja"
  },
  {
    "name": "Nina Badrić"
  },
  {
    "name": "Nipplepeople"
  },
  {
    "name": "Ničim Izazvan"
  },
  {
    "name": "Ništa Ali Logopedi"
  },
  {
    "name": "Novi Fosili"
  },
  {
    "name": "Obojeni Program"
  },
  {
    "name": "Ogi Radivojevic"
  },
  {
    "name": "Ognjen x Angellina"
  },
  {
    "name": "Nedeljko Bilkić"
  },
  {
    "name": "Oktobar 1864"
  },
  {
    "name": "Oliver Mandic"
  },
  {
    "name": "Olivera Marković (Bata Živojinović)"
  },
  {
    "name": "Orthodox Celts"
  },
  {
    "name": "Ortodox Celts"
  },
  {
    "name": "Osmi putnik"
  },
  {
    "name": "Osvajaci"
  },
  {
    "name": "Partibrejkers"
  },
  {
    "name": "Pesma iz filma"
  },
  {
    "name": "Piloti"
  },
  {
    "name": "Plavi Orkestar"
  },
  {
    "name": "Poslednja Igra Leptira"
  },
  {
    "name": "Prljavi Inspektor Blaža"
  },
  {
    "name": "Nemanja Nikolic"
  },
  {
    "name": "Nikola i Marko Rokvić"
  },
  {
    "name": "Prljavo Kazaliste"
  },
  {
    "name": "Pro Arte"
  },
  {
    "name": "Punkt"
  },
  {
    "name": "Zeljko Joksimovic"
  },
  {
    "name": "Nada Obrić"
  },
  {
    "name": "Narodna"
  },
  {
    "name": "Narodna crnogrska"
  },
  {
    "name": "Novica Negovanović"
  },
  {
    "name": "Novica Zdravković (M)"
  },
  {
    "name": "Sundjer Bob"
  },
  {
    "name": "Narodna pesma"
  },
  {
    "name": "narodna-sevdah"
  },
  {
    "name": "Narodne pesme"
  },
  {
    "name": "Neda Ukraden Dejan Matic"
  },
  {
    "name": "Nedeljko Bajic Baja"
  },
  {
    "name": "Tajci"
  },
  {
    "name": "Novica Zdravković"
  },
  {
    "name": "Ok Bend"
  },
  {
    "name": "Olja Karleusa"
  },
  {
    "name": "Partizanske pesme"
  },
  {
    "name": "Patos"
  },
  {
    "name": "Pedja Jovanovic"
  },
  {
    "name": "Queen"
  },
  {
    "name": "Predrag Cune Gojković"
  },
  {
    "name": "Prijovic Aleksandra"
  },
  {
    "name": "Nancy Sinatra"
  },
  {
    "name": "Nata"
  },
  {
    "name": "Nick Cave"
  },
  {
    "name": "Nikos Vertis"
  },
  {
    "name": "Nils Lofgren"
  },
  {
    "name": "Raconteurs"
  },
  {
    "name": "Nina Simone"
  },
  {
    "name": "Nirvana"
  },
  {
    "name": "No Doubt"
  },
  {
    "name": "Nouvelle Vague"
  },
  {
    "name": "One Republic"
  },
  {
    "name": "Pearl Jam"
  },
  {
    "name": "Psy"
  },
  {
    "name": "Rani Mraz"
  },
  {
    "name": "Rasta"
  },
  {
    "name": "Regata"
  },
  {
    "name": "Regina (Sarajevo)"
  },
  {
    "name": "Rezonansa"
  },
  {
    "name": "Riblja Corba"
  },
  {
    "name": "Rodja"
  },
  {
    "name": "Rokeri s Moravu"
  },
  {
    "name": "Romana"
  },
  {
    "name": "S vremena na vreme"
  },
  {
    "name": "Sale i Sedlari"
  },
  {
    "name": "Sara Jovanović"
  },
  {
    "name": "Radoslav Rodic Roki"
  },
  {
    "name": "Sasa Kovacevic"
  },
  {
    "name": "Satan Panonski"
  },
  {
    "name": "Saša Kovačević & Nikolina Pišek"
  },
  {
    "name": "Saša Lošić Loša"
  },
  {
    "name": "Saša Vasić"
  },
  {
    "name": "Rasa Pavlovic"
  },
  {
    "name": "Toto Cutugno"
  },
  {
    "name": "Seid Memić Vajta"
  },
  {
    "name": "Sergej Ćetković i Who See"
  },
  {
    "name": "SevdahBABY & Djixx"
  },
  {
    "name": "Severina"
  },
  {
    "name": "Sky Wikluh"
  },
  {
    "name": "Svilen Konac"
  },
  {
    "name": "Šaban Bajramović"
  },
  {
    "name": "Slađana Milošević"
  },
  {
    "name": "Sonja Savić"
  },
  {
    "name": "Srdjan Jul"
  },
  {
    "name": "Srdjan Marjanovic"
  },
  {
    "name": "Stijene"
  },
  {
    "name": "Šarlo Akrobata"
  },
  {
    "name": "Rada Manojlovic"
  },
  {
    "name": "Rada Manojlovic i Haris Berkovic"
  },
  {
    "name": "Rada Saric`"
  },
  {
    "name": "Rada Sarić & Miloš Brkić"
  },
  {
    "name": "Rade Kosmajac"
  },
  {
    "name": "Radiša Marković"
  },
  {
    "name": "Rizo Hamidovic"
  },
  {
    "name": "Rock ko fol"
  },
  {
    "name": "Saban Saulic"
  },
  {
    "name": "Safet Isović"
  },
  {
    "name": "Sako Polumenta"
  },
  {
    "name": "Šaban Šaulić i Zorica Brunclik"
  },
  {
    "name": "Radiohead"
  },
  {
    "name": "Sasa Matic"
  },
  {
    "name": "Sasa Matic i Ceca"
  },
  {
    "name": "Savo Radusinović"
  },
  {
    "name": "Sedmorica mladih"
  },
  {
    "name": "Sejo Kalač"
  },
  {
    "name": "Sejo Pitić"
  },
  {
    "name": "Seka Aleksic"
  },
  {
    "name": "Sekstet Skadarlija"
  },
  {
    "name": "Semsa Suljakovic"
  },
  {
    "name": "SEVDALINKA"
  },
  {
    "name": "Sevdalinke"
  },
  {
    "name": "Silvana Armenulić"
  },
  {
    "name": "Sinan Sakic"
  },
  {
    "name": "Sladja Allegro"
  },
  {
    "name": "Slavica Cukteras"
  },
  {
    "name": "Slavko Banjac"
  },
  {
    "name": "Slavko Petrović"
  },
  {
    "name": "Sloba Radanović"
  },
  {
    "name": "Sloba Radanović i Dara Bubamara"
  },
  {
    "name": "Slobodan Sloba Stojadinović"
  },
  {
    "name": "Slobodan Trkulja"
  },
  {
    "name": "Snežana Savić"
  },
  {
    "name": "Snježana Đurišić"
  },
  {
    "name": "Srećko Šušić"
  },
  {
    "name": "Srđan M"
  },
  {
    "name": "Staniša Stošić"
  },
  {
    "name": "Stari Zvuci"
  },
  {
    "name": "Starogradske"
  },
  {
    "name": "Starogradske pesme"
  },
  {
    "name": "Stoja & Dejan Matić"
  },
  {
    "name": "Svetlana Ceca Ražnatović"
  },
  {
    "name": "Svetlana Ceca Ražnatović i Oliver Mandić"
  },
  {
    "name": "Red Hot Chili Peppers"
  },
  {
    "name": "Rihanna"
  },
  {
    "name": "Robbie Williams"
  },
  {
    "name": "Robert Johnson"
  },
  {
    "name": "Roberta Flack"
  },
  {
    "name": "Rolling Stones (The)"
  },
  {
    "name": "Rolling Stones"
  },
  {
    "name": "Ross Lynch"
  },
  {
    "name": "Roxette"
  },
  {
    "name": "Roy Orbison"
  },
  {
    "name": "Ruske Pesme"
  },
  {
    "name": "Sam Smith"
  },
  {
    "name": "Tonci Huljic"
  },
  {
    "name": "Toni Montano"
  },
  {
    "name": "Scorpions"
  },
  {
    "name": "Shawn Mendes"
  },
  {
    "name": "Simple Minds"
  },
  {
    "name": "Steven Tyler"
  },
  {
    "name": "Stevie Ray Vaughan"
  },
  {
    "name": "Stevie Wonder"
  },
  {
    "name": "Sting"
  },
  {
    "name": "Tose i Tony"
  },
  {
    "name": "Stretch"
  },
  {
    "name": "System of a Down"
  },
  {
    "name": "Tanja Banjanin"
  },
  {
    "name": "Tap 011"
  },
  {
    "name": "Teatar"
  },
  {
    "name": "Tifa i Makadam"
  },
  {
    "name": "Tijana Dapčević"
  },
  {
    "name": "Tose Proeski"
  },
  {
    "name": "Tose Proeski i Antonija"
  },
  {
    "name": "Tropico Band"
  },
  {
    "name": "Tropico band i Dzenan Loncarevic"
  },
  {
    "name": "Tropico Band&Dzenan Loncarevic"
  },
  {
    "name": "Tropico Band,Sara Jo,Dzenan Loncarevic i Andrej Ilic"
  },
  {
    "name": "Trula koalicija"
  },
  {
    "name": "Toni Braxton"
  },
  {
    "name": "Tutti Frutti"
  },
  {
    "name": "Tutti Frutti Band"
  },
  {
    "name": "Tamburica 5"
  },
  {
    "name": "Tanja Savic"
  },
  {
    "name": "Thompson"
  },
  {
    "name": "Toma Zdravkovic"
  },
  {
    "name": "Toma Zdravković (M)"
  },
  {
    "name": "Tomislav Bralić & Klapa Intrade"
  },
  {
    "name": "Tomislav Ivčić"
  },
  {
    "name": "Tozovac, Predrag Živković"
  },
  {
    "name": "Terry Jack"
  },
  {
    "name": "The Doors"
  },
  {
    "name": "The Neighbourhood"
  },
  {
    "name": "the pointer sisters"
  },
  {
    "name": "The Rembrandts"
  },
  {
    "name": "The tallest man on earth"
  },
  {
    "name": "U Škripcu"
  },
  {
    "name": "Valentino"
  },
  {
    "name": "Vampiri"
  },
  {
    "name": "Vatra"
  },
  {
    "name": "Vatreni Poljubac"
  },
  {
    "name": "Veliki Prezir"
  },
  {
    "name": "Via Talas"
  },
  {
    "name": "Viktorija"
  },
  {
    "name": "Vještice"
  },
  {
    "name": "Vlada Divljan (Idoli)"
  },
  {
    "name": "Vlada Divljan"
  },
  {
    "name": "Vlada i Bajka"
  },
  {
    "name": "Vlado Georgiev"
  },
  {
    "name": "Vlado i Niggor"
  },
  {
    "name": "Vlado Janevski"
  },
  {
    "name": "Vlatko Stefanovski"
  },
  {
    "name": "voyage"
  },
  {
    "name": "Voyage x Breskvica"
  },
  {
    "name": "Vojislav Ilić"
  },
  {
    "name": "Vrapčići"
  },
  {
    "name": "Vuk Mob ft. Voyage x Breskvica"
  },
  {
    "name": "Xenia"
  },
  {
    "name": "Yu Rock Misija"
  },
  {
    "name": "Zabranjeno Pušenje"
  },
  {
    "name": "ZAFIR HADJIMANOV"
  },
  {
    "name": "Zana"
  },
  {
    "name": "Zdravko Colic"
  },
  {
    "name": "Zeljko"
  },
  {
    "name": "Zaim Imamovic"
  },
  {
    "name": "Zeljko Bebek"
  },
  {
    "name": "Zlatko & DAH"
  },
  {
    "name": "Zlatko Manojlović"
  },
  {
    "name": "Zlatko Pejaković"
  },
  {
    "name": "Željko Joksimović Toni cetinski"
  },
  {
    "name": "Željko Panonac"
  },
  {
    "name": "Usnija Redžepova"
  },
  {
    "name": "Vasilija Radojčić"
  },
  {
    "name": "Vera Matovic"
  },
  {
    "name": "Verica Serifovic"
  },
  {
    "name": "Vesna Zmijanac"
  },
  {
    "name": "Vida Pavlovic"
  },
  {
    "name": "Viki"
  },
  {
    "name": "Viki Miljković"
  },
  {
    "name": "Vlada Kanić"
  },
  {
    "name": "Zika Marinkovic"
  },
  {
    "name": "Zlata Petrović"
  },
  {
    "name": "Žarko Dančuo"
  },
  {
    "name": "Željko Šasić"
  },
  {
    "name": "Žika Antić"
  },
  {
    "name": "Žika Ivković"
  },
  {
    "name": "Uriah Heep"
  },
  {
    "name": "Ville Valo"
  },
  {
    "name": "Weezer"
  },
  {
    "name": "Whitesnake"
  },
  {
    "name": "Why Does My Heart Feel So Bad"
  },
  {
    "name": "Zaz"
  },
  {
    "name": "Aco Pejović"
  }
]